nucdens/__init__.py
nucdens/access.py
nucdens-1.2.0.dist-info/LICENSE
nucdens-1.2.0.dist-info/METADATA
nucdens-1.2.0.dist-info/WHEEL
nucdens-1.2.0.dist-info/top_level.txt
nucdens-1.2.0.dist-info/RECORD
